onnx_safetensors/__init__.py
onnx_safetensors/_cli.py
onnx_safetensors/_metadata.py
onnx_safetensors/_safetensors_io.py
onnx_safetensors/_tensors.py
onnx_safetensors/_type_casting.py
onnx_safetensors-1.5.0.dist-info/licenses/LICENSE
onnx_safetensors-1.5.0.dist-info/METADATA
onnx_safetensors-1.5.0.dist-info/WHEEL
onnx_safetensors-1.5.0.dist-info/entry_points.txt
onnx_safetensors-1.5.0.dist-info/top_level.txt
onnx_safetensors-1.5.0.dist-info/RECORD
