Metadata-Version: 2.4
Name: onnx-safetensors
Version: 1.5.0
Summary: Use safetensors with ONNX
Author-email: Justin Chu <justinchuby@users.noreply.github.com>
License: MIT License
Project-URL: Documentation, https://github.com/justinchuby/onnx-safetensors#readme
Project-URL: Issues, https://github.com/justinchuby/onnx-safetensors/issues
Project-URL: Source, https://github.com/justinchuby/onnx-safetensors
Classifier: Development Status :: 4 - Beta
Classifier: Environment :: Console
Classifier: Intended Audience :: Developers
Classifier: Operating System :: POSIX
Classifier: Operating System :: MacOS :: MacOS X
Classifier: Operating System :: Microsoft :: Windows
Classifier: Programming Language :: Python :: 3.9
Classifier: Programming Language :: Python :: 3.10
Classifier: Programming Language :: Python :: 3.11
Classifier: Programming Language :: Python :: 3.12
Classifier: Programming Language :: Python :: 3.13
Classifier: Programming Language :: Python :: 3.14
Classifier: License :: OSI Approved :: MIT License
Requires-Python: >=3.9
License-File: LICENSE
Requires-Dist: numpy
Requires-Dist: onnx>=1.16
Requires-Dist: safetensors
Requires-Dist: onnx-ir
Requires-Dist: tqdm
Dynamic: license-file
